{
    "slkjfv": {
        "points": 0,
        "password": "sdkjfnv"
    },
    "ksjdnfv": {
        "points": "0",
        "password": "kjsdnfv"
    },
    "jksdfv": {
        "points": 0,
        "password": "jksdfv"
    },
    "kjdfnv": {
        "points": "0",
        "password": "sdnfv"
    },
    "sdkjfn": {
        "points": 0,
        "password": "ljsndfv"
    },
    "kjdsnfv": {
        "points": "0",
        "password": "kjsdnfv"
    },
    "sdfkjv": {
        "points": 0,
        "password": "ljsnfv"
    },
    "kdjfgb": {
        "points": "0",
        "password": "jnfgb"
    },
    "klsdjnfv": {
        "points": 0,
        "password": "kjsndfv"
    },
    "lkdjfnv": {
        "points": "0",
        "password": "kjsdnf"
    },
    "knjdsfv": {
        "points": 0,
        "password": "kjsdnfv"
    },
    "skdfnv": {
        "points": "0",
        "password": "kjndsfv"
    },
    "lfgjnb": {
        "points": 0,
        "password": "dnfv"
    },
    "kjsdfv": {
        "points": "0",
        "password": "slkdjfv"
    },
    "ksjdnfvd": {
        "points": 0,
        "password": "kjnsdfv"
    },
    "kjdnsfv": {
        "points": "0",
        "password": "jsdnfv"
    },
    "ksjdsdjk": {
        "points": 0,
        "password": "sjdnfv"
    },
    "ksjdfv": {
        "points": "0",
        "password": "kljdsnf"
    },
    "jnsdfv": {
        "points": 0,
        "password": "jnsdfv"
    },
    "kjndsfv": {
        "points": "0",
        "password": "kjndsfv"
    },
    "kjsdf": {
        "points": 0,
        "password": "kjnsdfv"
    },
    "kjsdfdfv": {
        "points": 0,
        "password": "kjsdnfv"
    },
    "sjdnfv": {
        "points": "0",
        "password": "jsndfv"
    },
    "kdjfg": {
        "points": 0,
        "password": "kdjfngb"
    },
    "kjndsv": {
        "points": 0,
        "password": "kjndsfv"
    },
    "kljdsv": {
        "points": "0",
        "password": "kjsfdv"
    },
    "jsnfdv": {
        "points": 0,
        "password": "ksjndfv"
    },
    "ksjnfv": {
        "points": 0,
        "password": "jndsfv"
    },
    "kjsdnvf": {
        "points": "0",
        "password": "lskdjnf"
    },
    "ksjnfvkj": {
        "points": 0,
        "password": "kjdfv"
    },
    "sjdnfvvj": {
        "points": "0",
        "password": "skjdfv"
    },
    "dkjfnv": {
        "points": 0,
        "password": "skjdfnv"
    },
    "kdjnfgb": {
        "points": "0",
        "password": "kjnfdgb"
    },
    "kjndlfg": {
        "points": 0,
        "password": "jdfngb"
    },
    "jdnfv": {
        "points": "0",
        "password": "jsndf"
    },
    "ksdfv": {
        "points": 0,
        "password": "jdfv"
    },
    "dkjfng": {
        "points": 0,
        "password": "jnfgb"
    },
    "ndfv": {
        "points": "0",
        "password": "nsdfv"
    },
    "jdnfbg": {
        "points": 0,
        "password": "jgnfb"
    },
    "sjdnfvdf": {
        "points": "0",
        "password": "ndfv"
    },
    "sjnfv": {
        "points": 0,
        "password": "kjdnv"
    },
    "jndfgb": {
        "points": "0",
        "password": "dkjfngb"
    },
    "sjnv": {
        "points": 0,
        "password": "kjsndf"
    },
    "ksdnjf": {
        "points": "0",
        "password": "kjdnfv"
    },
    "kdjfnv": {
        "points": 0,
        "password": "kjsdfv"
    },
    "klsdjnfd": {
        "points": "0",
        "password": "jdsvf"
    },
    "klsjdnf\"": {
        "points": 0,
        "password": "dksfv"
    },
    "klsjdnfv": {
        "points": "0",
        "password": "kjsdnfv"
    },
    "jndfv": {
        "points": 0,
        "password": "jkndfv"
    },
    "kdjnfv": {
        "points": "0",
        "password": "kjnsfv"
    },
    "sljdnfv": {
        "points": 0,
        "password": "kjsdfv"
    },
    "kjsdnfv": {
        "points": "0",
        "password": "nsdfv"
    },
    "sdjnfv": {
        "points": 0,
        "password": "ksjndfv"
    },
    "ksjdfvdf": {
        "points": "0",
        "password": "sknjdvf"
    },
    "ksjndfv": {
        "points": 0,
        "password": "ksjndfv"
    },
    "ksjdvf": {
        "points": "0",
        "password": "kjsndfv"
    },
    "sjdfv": {
        "points": 0,
        "password": "kjndsfv"
    },
    "dksfjn": {
        "points": "0",
        "password": "sdjnfv"
    },
    "slnjdv": {
        "points": 0,
        "password": "ksjndvd"
    },
    "skdjnf": {
        "points": "0",
        "password": "jdnsfv"
    },
    "jdnfvdfv": {
        "points": 0,
        "password": "kjdnfv"
    },
    "sknjdf": {
        "points": "0",
        "password": "snjdfv"
    },
    "kdfjv": {
        "points": 0,
        "password": "sljndfv"
    },
    "klsjdvf": {
        "points": "0",
        "password": "kjsndfv"
    },
    "lksdjnf": {
        "points": 0,
        "password": "ksnjdfv"
    },
    "ksdjnfv": {
        "points": "0",
        "password": "ksjdfv"
    },
    "kjsdnfvd": {
        "points": 0,
        "password": "jsjdfv"
    },
    "dskjnfv": {
        "points": "0",
        "password": "kjsdfv"
    },
    "kjsdnf)": {
        "points": 0,
        "password": "jsndfv"
    },
    "kjsdnv": {
        "points": "0",
        "password": "jsdfv"
    },
    "jsndfv": {
        "points": 0,
        "password": "ksjnfv"
    },
    "sdjnfvkj": {
        "points": "0",
        "password": "jn"
    },
    "kjdnfgb": {
        "points": 0,
        "password": "djnfgb"
    },
    "kfdjb": {
        "points": "0",
        "password": "kjnfgb"
    },
    "dkjfng\"": {
        "points": 0,
        "password": "kdnfgb"
    },
    "kfngj": {
        "points": "0",
        "password": "kjfdg"
    },
    "lkdfnjgb": {
        "points": 0,
        "password": "kdfngb"
    },
    "kjsdfvj": {
        "points": 0,
        "password": "jnsdfv"
    },
    "kdjfv": {
        "points": "0",
        "password": "jsdfv"
    },
    "sdjkfv": {
        "points": 0,
        "password": "ksdnfv"
    },
    "kjdnv": {
        "points": "0",
        "password": "kjnsdfv"
    },
    "jksdnfv": {
        "points": 0,
        "password": "skdjnfv"
    },
    "kdjsnv": {
        "points": 0,
        "password": "ksjdnv"
    },
    "skjf": {
        "points": "0",
        "password": "kndjfv"
    },
    "ksdnjfv": {
        "points": 0,
        "password": "ksjdfv"
    },
    "skdnfv))": {
        "points": "0",
        "password": "jnsdfv"
    },
    "ksjndfvd": {
        "points": 0,
        "password": "kjsdfv"
    },
    "snkdjv": {
        "points": "0",
        "password": "njksdfv"
    },
    "kljdfgb": {
        "points": 0,
        "password": "kjdfgb"
    },
    "kjdgb": {
        "points": "0",
        "password": "kjndfgb"
    },
    "jnsdfvdv": {
        "points": 0,
        "password": "kjndsfv"
    },
    "kldfb": {
        "points": "0",
        "password": "dfkjgb"
    },
    "jdfn": {
        "points": 0,
        "password": "dfkngjb"
    },
    "kjndfb": {
        "points": 0,
        "password": "jnfdgb"
    },
    "slkfm": {
        "points": 0,
        "password": "skjnfdv"
    },
    "kdjlghn": {
        "points": 0,
        "password": "kjdfgb"
    },
    "lkjdf": {
        "points": 0,
        "password": "kjdf"
    },
    "kjdfv": {
        "points": 0,
        "password": "kjdsfv"
    },
    "kjdsfv": {
        "points": 0,
        "password": "jdfv"
    },
    "kvn": {
        "points": 0,
        "password": "sdfv"
    },
    "kjsfdv": {
        "points": 0,
        "password": "jnsdfv"
    },
    "kjnsfv": {
        "points": 0,
        "password": "knsfv"
    },
    "jsdfv": {
        "points": 0,
        "password": "nsdfv"
    },
    "njdfv": {
        "points": 0,
        "password": "jnsdfv"
    },
    "kjsdfj": {
        "points": 0,
        "password": "jnsdfv"
    },
    "kjsnfv": {
        "points": 0,
        "password": "kjsdfv"
    },
    "jnsfv": {
        "points": 0,
        "password": "kjnsdfv"
    },
    "reshilo": {
        "points": 0,
        "password": "123"
    },
    "lkjsdfv": {
        "points": 0,
        "password": "kjsdnfv"
    },
    "ljsndfv": {
        "points": 0,
        "password": "kjsdfv"
    },
    "jdfv": {
        "points": 0,
        "password": "jksdfv"
    },
    "kljdsnfv": {
        "points": 0,
        "password": "kjndsfv"
    },
    "kjndfgb": {
        "points": 0,
        "password": "dkjfgb"
    },
    "dbj": {
        "points": 0,
        "password": "ffdg"
    },
    "kjdfb": {
        "points": 0,
        "password": "dkjf"
    },
    "kdnf": {
        "points": 0,
        "password": "bn"
    },
    "kjns": {
        "points": 0,
        "password": "klnsdf"
    },
    "knd45": {
        "points": 0,
        "password": "kj"
    },
    "kljnsvf": {
        "points": 0,
        "password": "jnsdfv"
    },
    "jnsdfvv": {
        "points": 0,
        "password": "kjnsdfv"
    },
    "ndb": {
        "points": 0,
        "password": "jdfbg"
    },
    "skdnjfv": {
        "points": 0,
        "password": "sndfv"
    },
    "kjndsfvd": {
        "points": 0,
        "password": "kjnsdv"
    },
    "kjsdfvv": {
        "points": 0,
        "password": "ljsnfv"
    },
    "sdfv": {
        "points": 0,
        "password": "dfv"
    },
    "lkmsfv": {
        "points": 0,
        "password": "slkdfv"
    },
    "kjf": {
        "points": 0,
        "password": "kfmv"
    },
    "lkmsd": {
        "points": 0,
        "password": "lskdc"
    },
    "nsldc": {
        "points": 0,
        "password": "lksadc"
    },
    "las;": {
        "points": 0,
        "password": "lasc"
    },
    "sdkfnjv": {
        "points": 0,
        "password": "kjsdv"
    },
    "skjdfv": {
        "points": 0,
        "password": "klmd"
    },
    "lndkf": {
        "points": 0,
        "password": "lkdf"
    },
    "loveme": {
        "points": 0,
        "password": "1234"
    },
    "vova": {
        "points": 0,
        "password": "1234"
    },
    "dkfjb": {
        "points": 0,
        "password": "kdjgfb"
    },
    "ksjdnf": {
        "points": 0,
        "password": "jsdf"
    },
    "kjsv": {
        "points": 0,
        "password": "kjsdfv"
    },
    "dslc": {
        "points": 0,
        "password": "l;s,cd"
    },
    "sok": {
        "points": 0,
        "password": "masc"
    },
    "lksdmv": {
        "points": 0,
        "password": "kmdfv"
    },
    "lsd": {
        "points": 0,
        "password": "akslmd"
    },
    "vnj": {
        "points": 0,
        "password": "dv"
    },
    "la": {
        "points": 0,
        "password": "sadc"
    },
    "kjdsf": {
        "points": 0,
        "password": "jknsdf"
    },
    "ksdv": {
        "points": 0,
        "password": "klmsdv"
    },
    ";dkv": {
        "points": 0,
        "password": "sldv"
    },
    "kmv": {
        "points": 0,
        "password": "lks"
    },
    "skjd": {
        "points": 0,
        "password": "kdv"
    },
    "kdv": {
        "points": 0,
        "password": "km"
    },
    "sjdv": {
        "points": 0,
        "password": "kjdv"
    },
    "kl": {
        "points": 0,
        "password": "ldkmf"
    },
    "sdjnv": {
        "points": 0,
        "password": "kjsdv"
    },
    "kdsv": {
        "points": 0,
        "password": "ksdv"
    },
    "lsdfv": {
        "points": 0,
        "password": "kdfv"
    },
    "lsmdfv": {
        "points": 0,
        "password": "klmsdfv"
    },
    "sdfvv": {
        "points": 0,
        "password": "sdfv"
    },
    "sv": {
        "points": 0,
        "password": "dsfv"
    },
    "klsdfv": {
        "points": 0,
        "password": "dfv"
    },
    "fn": {
        "points": 0,
        "password": "df"
    },
    "jdfg": {
        "points": 0,
        "password": "dfgb"
    },
    "fdb": {
        "points": 0,
        "password": "dfgb"
    },
    "ura": {
        "points": 0,
        "password": "lm"
    },
    "lkfm": {
        "points": 0,
        "password": "kfgb"
    },
    "dfv": {
        "points": 0,
        "password": "sfv"
    },
    "kjfn": {
        "points": 0,
        "password": "dfv"
    },
    "jdkfv": {
        "points": 0,
        "password": "dfv"
    },
    "dfnb": {
        "points": 0,
        "password": "dd"
    },
    "jkdf": {
        "points": 0,
        "password": "skdjnv"
    },
    "kjn": {
        "points": 0,
        "password": "jdnfg"
    },
    "dfjkn": {
        "points": 0,
        "password": "skjdfv"
    },
    "skldf": {
        "points": 0,
        "password": "msv"
    },
    "lkdvf": {
        "points": 0,
        "password": "lmkfv"
    },
    "kv": {
        "points": 0,
        "password": "dfv"
    },
    "ksdfvv": {
        "points": 0,
        "password": "dsfv"
    },
    "ksdjv": {
        "points": 0,
        "password": "jdfv"
    },
    "fdjkv": {
        "points": 0,
        "password": "fnnj"
    },
    "kjsfnd": {
        "points": 0,
        "password": "sdjnf"
    },
    "asdlkmc": {
        "points": 0,
        "password": "klsdc"
    },
    "aga": {
        "points": 0,
        "password": "klfmg"
    },
    "jdf": {
        "points": 0,
        "password": "jkndf"
    },
    "fmgb": {
        "points": 0,
        "password": "kmdfg"
    },
    "klb": {
        "points": 0,
        "password": "gnh"
    },
    "fgn": {
        "points": 0,
        "password": "hngh"
    },
    "lkfml": {
        "points": 0,
        "password": "flkgb"
    },
    "mfv": {
        "points": 0,
        "password": "lkdfv"
    },
    "klmb": {
        "points": 0,
        "password": "fgb"
    },
    "kfdv": {
        "points": 0,
        "password": "dfv"
    },
    "flkb": {
        "points": 0,
        "password": "lkmfg"
    },
    "dlkfv": {
        "points": 0,
        "password": "dfv"
    },
    "kmdv": {
        "points": 0,
        "password": "lmdkfv"
    },
    "mf": {
        "points": 0,
        "password": "kdfv"
    },
    "smdv": {
        "points": 0,
        "password": "kmdfv"
    },
    "dkfv": {
        "points": 0,
        "password": "kdv"
    },
    "ldmv": {
        "points": 0,
        "password": "kmdvf"
    },
    "kgfb": {
        "points": 0,
        "password": "lmkfg"
    },
    "fkgmb": {
        "points": 0,
        "password": "fmgb"
    },
    "lfkgmb": {
        "points": 0,
        "password": "gb"
    },
    "fnln": {
        "points": 0,
        "password": "fjmjm"
    },
    "lkmgh": {
        "points": 0,
        "password": "kghn"
    },
    "mklgf": {
        "points": 0,
        "password": "fmgb"
    },
    "kfg": {
        "points": 0,
        "password": "fkmgb"
    },
    "lkfmb": {
        "points": 0,
        "password": "ghn"
    },
    "kfm45": {
        "points": 0,
        "password": "gb"
    },
    "kjdnvd": {
        "points": 0,
        "password": "jndfv"
    },
    "dmv": {
        "points": 0,
        "password": "kdfv"
    },
    "kdfv": {
        "points": 0,
        "password": "jdfv"
    },
    "lkfg": {
        "points": 0,
        "password": "fkgb"
    },
    "kjdf": {
        "points": 0,
        "password": "jfgb"
    },
    "fgb": {
        "points": 0,
        "password": "gbg"
    },
    "kjfngb": {
        "points": 0,
        "password": "fgb"
    },
    "kfgb": {
        "points": 0,
        "password": "lfgb"
    },
    "klsdm": {
        "points": 0,
        "password": "kmfdv"
    },
    "lgfb": {
        "points": 0,
        "password": "fgb"
    },
    "horosya": {
        "points": 0,
        "password": "djfv"
    },
    "jv": {
        "points": 0,
        "password": "ksjdv"
    },
    "ldkfv": {
        "points": 0,
        "password": "kfmgb"
    },
    "kfgbgn": {
        "points": 0,
        "password": "kghn"
    },
    "djnfv": {
        "points": 0,
        "password": "jdnf"
    },
    "lkd": {
        "points": 0,
        "password": "kmdfv"
    },
    "jkfg": {
        "points": 0,
        "password": "lkmdfv"
    },
    "jf": {
        "points": 0,
        "password": "ff"
    },
    "klfg": {
        "points": 0,
        "password": "lkfg"
    },
    "lk": {
        "points": 0,
        "password": "kml"
    },
    "kjdfdv": {
        "points": 0,
        "password": "dfv"
    },
    "fbg": {
        "points": 0,
        "password": "gbg"
    },
    "lkdf": {
        "points": 0,
        "password": "mdfv"
    },
    "kmdfdfv": {
        "points": 0,
        "password": "lmdfv"
    },
    "jdfvvv": {
        "points": 0,
        "password": "kjdfv"
    },
    "lkmdfv": {
        "points": 0,
        "password": "kmdfv"
    },
    "ldf": {
        "points": 0,
        "password": "mdfv"
    },
    "sdlk": {
        "points": 0,
        "password": "lksdmv"
    },
    "ld": {
        "points": 0,
        "password": "ldkf"
    },
    "dl": {
        "points": 0,
        "password": "ldkfv"
    },
    "dkl": {
        "points": 0,
        "password": "dkf"
    },
    "df": {
        "points": 0,
        "password": "dfv"
    },
    "lkdffgb": {
        "points": 0,
        "password": "ldfv"
    },
    "dff": {
        "points": 0,
        "password": "dfv"
    },
    "lfg": {
        "points": 0,
        "password": "lkfgb"
    },
    "dk": {
        "points": 0,
        "password": "dfv"
    },
    "dfk": {
        "points": 0,
        "password": "kdf"
    },
    "lkg": {
        "points": 0,
        "password": "kfg"
    },
    "klfgf": {
        "points": 0,
        "password": "fgb"
    },
    "dferf": {
        "points": 0,
        "password": "fdv"
    },
    "fgkmb": {
        "points": 0,
        "password": "kmfgb"
    },
    "kfgfgb": {
        "points": 0,
        "password": "mkfgb"
    },
    "hglkn": {
        "points": 0,
        "password": "kghn"
    },
    "lmfg": {
        "points": 0,
        "password": "kfgb"
    },
    "kmb": {
        "points": 0,
        "password": "kgmhn"
    },
    "dfm": {
        "points": 0,
        "password": "kdfv"
    },
    "lkfb": {
        "points": 0,
        "password": "fmgb"
    },
    "fgk": {
        "points": 0,
        "password": "lkmfb"
    },
    "kjdv": {
        "points": 0,
        "password": "kjdfv"
    },
    "dflk": {
        "points": 0,
        "password": "ldkmfv"
    },
    "jnd": {
        "points": 0,
        "password": "dnfv"
    },
    "fkjng": {
        "points": 0,
        "password": "dfgb"
    },
    "kjdfk": {
        "points": 0,
        "password": "fgjbdf"
    },
    "dlkfm": {
        "points": 0,
        "password": "kjsndfv"
    },
    "ladno": {
        "points": 0,
        "password": "kmfgb"
    },
    "lkdmfb": {
        "points": 0,
        "password": "dkfmlgb"
    },
    "kjdfsn": {
        "points": 0,
        "password": "dfkjv"
    },
    "nsdfv": {
        "points": 0,
        "password": "ndfv"
    },
    "kjfndv": {
        "points": 0,
        "password": "jdsfv"
    },
    "ksjdnlkf": {
        "points": 0,
        "password": "jksndfv"
    },
    "kjdfvdfv": {
        "points": 0,
        "password": "ksfdv"
    },
    "skdfv": {
        "points": 0,
        "password": "lksdfv"
    },
    "sldkf": {
        "points": 0,
        "password": "kmsdfv"
    },
    "lsdkf": {
        "points": 0,
        "password": "smdfv"
    },
    "kjsndfv": {
        "points": 0,
        "password": "jndsfv"
    },
    "kjsdfvdl": {
        "points": 0,
        "password": "jnsdfv"
    },
    "skdjv": {
        "points": 0,
        "password": "jsdfv"
    },
    "dkjfnvdf": {
        "points": 0,
        "password": "lkdfv"
    },
    "kdfnv": {
        "points": 0,
        "password": "jndfv"
    },
    "skjnfv": {
        "points": 0,
        "password": "jnsdfv"
    },
    "kjdfvdfl": {
        "points": 0,
        "password": "jnsdfv"
    },
    "sklmd": {
        "points": 0,
        "password": "lmdfv"
    },
    "l;sdc": {
        "points": 0,
        "password": "lsdc"
    },
    "dskfv": {
        "points": 0,
        "password": "jnsdfv"
    },
    "kdfvdv": {
        "points": 0,
        "password": "kdfv"
    },
    "ldmfv": {
        "points": 0,
        "password": "kdfv"
    },
    "skdnfv": {
        "points": 0,
        "password": "kjsdfv"
    },
    "sfv": {
        "points": 0,
        "password": "sdfv"
    },
    "kdjngb": {
        "points": 0,
        "password": "ndfgb"
    },
    "kjnlkm": {
        "points": 0,
        "password": "hb"
    },
    "jdnf": {
        "points": 0,
        "password": "kjndfv"
    },
    "dfvvdf": {
        "points": 0,
        "password": "dfv"
    },
    "kdjn": {
        "points": 0,
        "password": "jndsfv"
    },
    "kjdvl": {
        "points": 0,
        "password": "jsdfv"
    },
    "jsnfd": {
        "points": 0,
        "password": "jsdfv"
    },
    "ndv": {
        "points": 0,
        "password": "jsdfv"
    },
    "knsdv": {
        "points": 0,
        "password": "kjsdfv"
    },
    "kjsdv": {
        "points": 0,
        "password": "kjnsfv"
    },
    "jsndfvdv": {
        "points": 0,
        "password": "jnsdfv"
    },
    "kdfn": {
        "points": 0,
        "password": "kjsdf"
    },
    "osa": {
        "points": 0,
        "password": "kdjnv"
    },
    "ksn": {
        "points": 0,
        "password": "kjnsfv"
    },
    "ksdn": {
        "points": 0,
        "password": "jsndf"
    },
    "dkfj": {
        "points": 0,
        "password": "jsndfv"
    },
    "knsdvnj": {
        "points": 0,
        "password": "kdnsfv"
    },
    "jsndf": {
        "points": 0,
        "password": "snjfv"
    },
    "sjndv": {
        "points": 0,
        "password": "ljsdfv"
    },
    "kjdvdv": {
        "points": 0,
        "password": "jksdfv"
    },
    "jkfv": {
        "points": 0,
        "password": "nsdfv"
    },
    "jndsfv": {
        "points": 0,
        "password": "kjnsdf"
    },
    "kjdfvsdv": {
        "points": 0,
        "password": "ksjdvf"
    },
    "kjsdvsdf": {
        "points": 0,
        "password": "kjsdfv"
    },
    "kjndsvsd": {
        "points": 0,
        "password": "skjdvnj"
    },
    "kjsndfvs": {
        "points": 0,
        "password": "kjsfv"
    },
    "jsdnfv": {
        "points": 0,
        "password": "sjdfv"
    },
    "kjndsfgd": {
        "points": 0,
        "password": "kjsdfvs"
    },
    "ksjdnfvs": {
        "points": 0,
        "password": "jndsfv"
    },
    "sjndf": {
        "points": 0,
        "password": "kjsdfv"
    },
    "sjndfv": {
        "points": 0,
        "password": "jsndfv"
    },
    "jkndsfv": {
        "points": 0,
        "password": "kjsndfv"
    },
    "kjsdfsdf": {
        "points": 0,
        "password": "jnsdf"
    },
    "ksjndfvs": {
        "points": 0,
        "password": "sndfv"
    },
    "jsdfvsdf": {
        "points": 0,
        "password": "ndfv"
    },
    "kjsdvdfv": {
        "points": 0,
        "password": "jknsdv"
    },
    "kjsndfvd": {
        "points": 0,
        "password": "kjnsdfv"
    },
    "jnsdvf": {
        "points": 0,
        "password": "nsdfv"
    },
    "snjdfv": {
        "points": 0,
        "password": "jnsdfv"
    },
    "jknsdv": {
        "points": 0,
        "password": "jnsdfv"
    },
    "ljsdfv": {
        "points": 0,
        "password": "kjsdfv"
    },
    "ksdfvdsf": {
        "points": 0,
        "password": "kmsdfv"
    }
}