{
    "kdjfnv": {
        "points": 0,
        "password": "jdfvd"
    },
    "dkfjnvd": {
        "points": "0",
        "password": "kfjdnv"
    },
    "dkjfnv": {
        "points": 0,
        "password": "kjdnfv"
    },
    "kdjfnvdv": {
        "points": "0",
        "password": "jdfnv"
    },
    "dkfjnv": {
        "points": 0,
        "password": "kdjfnv"
    },
    "kjdfnvdd": {
        "points": "0",
        "password": "kjndfv"
    },
    "jfnv": {
        "points": 0,
        "password": "djkfnv"
    },
    "kenji": {
        "points": "0",
        "password": "dkjfnv"
    },
    "kdfjnv": {
        "points": 0,
        "password": "kdjnfv"
    },
    "fnvdfv": {
        "points": "0",
        "password": "kjdnfv"
    },
    "kndv56": {
        "points": 0,
        "password": "jndfv"
    },
    "dinamoki": {
        "points": "0",
        "password": "kdnv"
    },
    "knjvf": {
        "points": 0,
        "password": "kjndfv"
    },
    "lndv": {
        "points": "0",
        "password": "kndv"
    },
    "vovavvdf": {
        "points": 0,
        "password": "2343"
    },
    "barabulk": {
        "points": "0",
        "password": "fjkv"
    },
    "djfnv": {
        "points": 0,
        "password": "djfnv"
    },
    "kjdfv": {
        "points": "0",
        "password": "vndfjk"
    },
    "djfnvdv": {
        "points": 0,
        "password": "dkjfnv"
    }
}